alx/__init__.py
alx/alx.ini
alx/app.py
alx/db_util.py
alx/html.py
alx/mail.py
alx/strings.py
alx/itrs/__init__.py
alx/itrs/alert.py
alx/itrs/environment.py
alx/itrs/toolkit.py
alx_common-2.8.8.dist-info/licenses/LICENSE.md
alx_common-2.8.8.dist-info/METADATA
alx_common-2.8.8.dist-info/WHEEL
alx_common-2.8.8.dist-info/top_level.txt
alx_common-2.8.8.dist-info/RECORD
