Metadata-Version: 2.4
Name: alx-common
Version: 2.8.8
Summary: An application framework promoting consistency and centralising common tasks
Author-email: Andrew Lister <andrew.lister@outlook.co.id>
License-Expression: GPL-3.0-or-later
Project-URL: Homepage, https://github.com/AndrewAPAC/alx-common
Project-URL: Examples, https://github.com/AndrewAPAC/alx-common/tree/main/examples
Project-URL: Changelog, https://github.com/AndrewAPAC/alx-common/blob/main/CHANGELOG.md
Project-URL: Issues, https://github.com/AndrewAPAC/alx-common/issues
Project-URL: Documentation, https://andrewapac.github.io/alx-common/
Project-URL: Discussion, https://github.com/AndrewAPAC/alx-common/discussions
Classifier: Development Status :: 5 - Production/Stable
Classifier: Intended Audience :: Developers
Classifier: Programming Language :: Python
Classifier: Programming Language :: Python :: 3.10
Classifier: Programming Language :: Python :: 3.11
Classifier: Programming Language :: Python :: 3.12
Classifier: Programming Language :: Python :: 3.13
Classifier: Programming Language :: Python :: 3.14
Classifier: Operating System :: OS Independent
Classifier: Topic :: Software Development :: Libraries
Classifier: Topic :: Utilities
Requires-Python: >=3.10
License-File: LICENSE.md
Requires-Dist: sql-formatter
Requires-Dist: cryptography
Requires-Dist: unidecode
Requires-Dist: DateTime
Requires-Dist: humanize
Requires-Dist: requests
Dynamic: license-file
